nbdev_pypi_broken/__init__.py
nbdev_pypi_broken/_modidx.py
nbdev_pypi_broken/core.py
nbdev_pypi_broken-0.0.1.dist-info/licenses/LICENSE
nbdev_pypi_broken-0.0.1.dist-info/METADATA
nbdev_pypi_broken-0.0.1.dist-info/WHEEL
nbdev_pypi_broken-0.0.1.dist-info/entry_points.txt
nbdev_pypi_broken-0.0.1.dist-info/top_level.txt
nbdev_pypi_broken-0.0.1.dist-info/RECORD
